pdsql/__init__.py
pdsql/mssql.py
pdsql/util.py
pdsql-1.2.34.dist-info/LICENSE.txt
pdsql-1.2.34.dist-info/METADATA
pdsql-1.2.34.dist-info/WHEEL
pdsql-1.2.34.dist-info/top_level.txt
pdsql-1.2.34.dist-info/RECORD
